topsis.py
topsis_devansh_102317041-2.0.dist-info/licenses/LICENSE
topsis_devansh_102317041-2.0.dist-info/METADATA
topsis_devansh_102317041-2.0.dist-info/WHEEL
topsis_devansh_102317041-2.0.dist-info/entry_points.txt
topsis_devansh_102317041-2.0.dist-info/top_level.txt
topsis_devansh_102317041-2.0.dist-info/RECORD
