Metadata-Version: 2.4
Name: Topsis-Devansh-102317041
Version: 2.0
Summary: A Python package for TOPSIS
Author-email: Devansh Chhabra <devanshchhabr@gmail.com>
Project-URL: Homepage, https://github.com/Devansh-Chhabra/TOPSIS-PyPi-Package
Classifier: Programming Language :: Python :: 3
Classifier: License :: OSI Approved :: MIT License
Classifier: Operating System :: OS Independent
Requires-Python: >=3.6
License-File: LICENSE
Dynamic: license-file
